<?xml version="1.0" encoding="UTF-8"?>
<prefab>
  <property name="CopyAirBlocks" value="True" />
  <property name="AllowTopSoilDecorations" value="True" />
  <property name="TraderArea" value="False" />
  <property name="ExcludeDistantPOIMesh" value="False" />
  <property name="ExcludePOICulling" value="False" />
  <property name="QuestTags" value="clear,fetch,hidden_cache" />
  <property name="DifficultyTier" value="1" />
  <property name="Zoning" value="Commercial, Downtown, Industrial, ResidentialNew, ResidentialOld, Residential" />
  <property name="RotationToFaceNorth" value="0" />
  <property name="YOffset" value="-10" />
  <property name="DistantPOIYOffset" value="0" />
  <property name="AllowedBiomes" value="burnt_forest,snow,plains,pine_forest,forest,desert,wasteland" />
  <property name="AllowedTownships" value="city,rural,town" />
  <property name="EditorGroups" value="Wilderness" />
  <property name="SleeperVolumeStart" value="9, 10, 7#17, 1, 25#9, 13, 7" />
  <property name="SleeperVolumeSize" value="15, 2, 15#13, 3, 11#15, 2, 15" />
  <property name="SleeperVolumeGroup" value="S_-Group_Generic_Zombie,3,4,S_-_Group_Zom_Badass,3,4,S_-Group_Generic_Zombie,1,2" />
  <property name="SleeperVolumeGameStageAdjust" value="," />
  <property name="SleeperIsLootVolume" value="False,False,False" />
  <property name="SleeperIsBossVolume" value="False,False" />
  <property name="SleeperVolumeFlags" value="0,0,0" />
  <property name="SleeperVolumeGroupId" value="0,0,0" />
  <property name="ShowQuestClearCount" value="1" />
  <property name="SleeperIsQuestExclude" value="False,False,False" />
  <property name="PrefabSize" value="42, 19, 42" />
  <property name="Tags" value="industrial" />
  <property class="IndexedBlockOffsets">
    <property class="POILight">
      <property name="0" value="35, 18, 39" />
    </property>
    <property class="FetchContainer">
      <property name="0" value="17, 1, 35" />
    </property>
    <property class="quest_feather">
      <property name="0" value="22, 15, 7" />
    </property>
    <property class="TraderOnOff">
      <property name="0" value="18, 12, 20" />
    </property>
    <property class="Rally">
      <property name="0" value="33, 10, 36" />
    </property>
  </property>
  <property class="Stats">
    <property name="TotalVertices" value="351608" />
    <property name="TotalTriangles" value="407951" />
    <property class="BlockEntities">
      <property name="Vertices" value="311040" />
      <property name="Triangles" value="375988" />
    </property>
    <property class="ChunkMeshes0">
      <property name="Vertices" value="31699" />
      <property name="Triangles" value="19403" />
    </property>
    <property class="ChunkMeshes1">
      <property name="Vertices" value="0" />
      <property name="Triangles" value="0" />
    </property>
    <property class="ChunkMeshes2">
      <property name="Vertices" value="208" />
      <property name="Triangles" value="144" />
    </property>
    <property class="ChunkMeshes3">
      <property name="Vertices" value="0" />
      <property name="Triangles" value="0" />
    </property>
    <property class="ChunkMeshes4">
      <property name="Vertices" value="1577" />
      <property name="Triangles" value="804" />
    </property>
    <property class="ChunkMeshes5">
      <property name="Vertices" value="0" />
      <property name="Triangles" value="0" />
    </property>
    <property class="ChunkMeshes6">
      <property name="Vertices" value="0" />
      <property name="Triangles" value="0" />
    </property>
    <property class="ChunkMeshes7">
      <property name="Vertices" value="7084" />
      <property name="Triangles" value="11612" />
    </property>
    <property class="ChunkMeshes8">
      <property name="Vertices" value="0" />
      <property name="Triangles" value="0" />
    </property>
    <property class="ChunkMeshes9">
      <property name="Vertices" value="0" />
      <property name="Triangles" value="0" />
    </property>
  </property>
</prefab>